<annotation>
	<folder>Flammable solid</folder>
	<filename>Flammable S128.jpg</filename>
	<path>C:\Users\Felipe Catapano\Documents\GitHub\K1D-RoboCup-RMRC-2023\Hazmat_identification_V2\Hazmat Datasets\Flammable solid\Flammable S128.jpg</path>
	<source>
		<database>Unknown</database>
	</source>
	<size>
		<width>500</width>
		<height>500</height>
		<depth>3</depth>
	</size>
	<segmented>0</segmented>
	<object>
		<name>Flammable solid</name>
		<pose>Unspecified</pose>
		<truncated>0</truncated>
		<difficult>0</difficult>
		<bndbox>
			<xmin>83</xmin>
			<ymin>78</ymin>
			<xmax>416</xmax>
			<ymax>423</ymax>
		</bndbox>
	</object>
</annotation>
