<annotation>
	<folder>Radioactive</folder>
	<filename>Radioc125.jpg</filename>
	<path>C:\Users\Felipe Catapano\Documents\GitHub\K1D-RoboCup-RMRC-2023\Hazmat_identification_V2\Hazmat Datasets\Radioactive\Radioc125.jpg</path>
	<source>
		<database>Unknown</database>
	</source>
	<size>
		<width>520</width>
		<height>520</height>
		<depth>3</depth>
	</size>
	<segmented>0</segmented>
	<object>
		<name>Radioactive</name>
		<pose>Unspecified</pose>
		<truncated>0</truncated>
		<difficult>0</difficult>
		<bndbox>
			<xmin>56</xmin>
			<ymin>311</ymin>
			<xmax>126</xmax>
			<ymax>384</ymax>
		</bndbox>
	</object>
	<object>
		<name>Radioactive</name>
		<pose>Unspecified</pose>
		<truncated>0</truncated>
		<difficult>0</difficult>
		<bndbox>
			<xmin>325</xmin>
			<ymin>291</ymin>
			<xmax>398</xmax>
			<ymax>364</ymax>
		</bndbox>
	</object>
</annotation>
